setup.py
probability_operations/Binomialdistribution.py
probability_operations/Gaussiandistribution.py
probability_operations/Generaldistribution.py
probability_operations/__init__.py
probability_operations.egg-info/PKG-INFO
probability_operations.egg-info/SOURCES.txt
probability_operations.egg-info/dependency_links.txt
probability_operations.egg-info/not-zip-safe
probability_operations.egg-info/top_level.txt