Metadata-Version: 1.0
Name: probability-operations
Version: 0.1
Summary: Gaussian distributions, Binomial Distributions
Home-page: UNKNOWN
Author: Biraj De
Author-email: birajde9@gmail.com
License: UNKNOWN
Platform: UNKNOWN
